{
  "message_type": "json",
  "patient": {
    "id": "123456",
    "name": [
      {
        "given": ["Jane"],
        "family": "Doe"
      }
    ],
    "gender": "female",
    "birth_date": "1985-03-15"
  },
  "provider": {
    "id": "PROV001",
    "name": "Dr. Emily Carter",
    "department": "Radiology"
  },
  "study": {
    "date": "2025-05-12",
    "accession_number": "ACC20250512001",
    "modality": "MG",
    "procedure_code": {
      "code": "24606-6",
      "system": "http://loinc.org",
      "display": "Mammogram Diagnostic Report"
    },
    "study_instance_uid": "1.2.840.113619.2.55.3.604688351.100.100.10000000000000000000"
  },
  "findings": [
    {
      "type": "rtf",
      "value": "{\\rtf \\line\\par\\trowd\\clbrdrt\\brdrs\\clbrdrl\\brdrs\\clbrdrb\\brdrs\\clbrdrr\\brdrs\\cellx1000 \\clbrdrt\\brdrs\\clbrdrl\\brdrs\\clbrdrb\\brdrs\\clbrdrr\\brdrs\\cellx2000\n\\clbrdrt\\brdrs\\clbrdrl\\brdrs\\clbrdrb\\brdrs\\clbrdrr\\brdrs\\cellx5000 \\fs16\\intbl \\cell \\fs16\\intbl \\cell \\fs16\\intbl Date du scanner: 2021-11-\n09\\cell\\row\\trowd\\clbrdrt\\brdrs\\clbrdrl\\brdrs\\clbrdrb\\brdrs\\clbrdrr\\brdrs\\cellx1000 \\clbrdrt\\brdrs\\clbrdrl\\brdrs\\clbrdrb\\brdrs\\clbrdrr\\brdrs\\cellx2000\n\\clbrdrt\\brdrs\\clbrdrl\\brdrs\\clbrdrb\\brdrs\\clbrdrr\\brdrs\\cellx3000 \\clbrdrt\\brdrs\\clbrdrl\\brdrs\\clbrdrb\\brdrs\\clbrdrr\\brdrs\\cellx4000 \\clbrdrt\\brdrs\\clbrdrl\\brdrs\\clbrdrb\\brdrs\\clbrdrr\\brdrs\\cellx5000\n\\fs16\\intbl Nodule \\cell \\fs16\\intbl Type de nodule \\cell \\fs16\\intbl Localisation du nodule \\cell \\fs16\\intbl Taille 2D grand axe \\cell \\fs16\\intbl Volume \\cell\n\\row\\trowd\\clbrdrt\\brdrs\\clbrdrl\\brdrs\\clbrdrb\\brdrs\\clbrdrr\\brdrs\\cellx1000 \\clbrdrt\\brdrs\\clbrdrl\\brdrs\\clbrdrb\\brdrs\\clbrdrr\\brdrs\\cellx2000\n\\clbrdrt\\brdrs\\clbrdrl\\brdrs\\clbrdrb\\brdrs\\clbrdrr\\brdrs\\cellx3000 \\clbrdrt\\brdrs\\clbrdrl\\brdrs\\clbrdrb\\brdrs\\clbrdrr\\brdrs\\cellx4000\n\\clbrdrt\\brdrs\\clbrdrl\\brdrs\\clbrdrb\\brdrs\\clbrdrr\\brdrs\\cellx5000\\fs16\\intbl N1\\cell\\fs16\\intbl solide\\cell\\fs16\\intbl Coupe 311\\cell\\fs16\\intbl 5\\cell\\fs16\\intbl 48\\cell\\row\n\\trowd\\clbrdrt\\brdrs\\clbrdrl\\brdrs\\clbrdrb\\brdrs\\clbrdrr\\brdrs\\cellx1000 \\clbrdrt\\brdrs\\clbrdrl\\brdrs\\clbrdrb\\brdrs\\clbrdrr\\brdrs\\cellx2000 \\clbrdrt\\brdrs\\clbrdrl\\brdrs\\clbrdrb\\brdrs\\clbrdrr\\brdrs\\cellx3000\n\\clbrdrt\\brdrs\\clbrdrl\\brdrs\\clbrdrb\\brdrs\\clbrdrr\\brdrs\\cellx4000 \\clbrdrt\\brdrs\\clbrdrl\\brdrs\\clbrdrb\\brdrs\\clbrdrr\\brdrs\\cellx5000\\fs16\\intbl N2\\cell\\fs16\\intbl solide\\cell\\fs16\\intbl Coupe\n310\\cell\\fs16\\intbl 7\\cell\\fs16\\intbl 50\\cell\\row \\trowd\\clbrdrt\\brdrs\\clbrdrl\\brdrs\\clbrdrb\\brdrs\\clbrdrr\\brdrs\\cellx1000 \\clbrdrt\\brdrs\\clbrdrl\\brdrs\\clbrdrb\\brdrs\\clbrdrr\\brdrs\\cellx2000\n\\clbrdrt\\brdrs\\clbrdrl\\brdrs\\clbrdrb\\brdrs\\clbrdrr\\brdrs\\cellx3000 \\clbrdrt\\brdrs\\clbrdrl\\brdrs\\clbrdrb\\brdrs\\clbrdrr\\brdrs\\cellx4000\n\\clbrdrt\\brdrs\\clbrdrl\\brdrs\\clbrdrb\\brdrs\\clbrdrr\\brdrs\\cellx5000\\fs16\\intbl N3\\cell\\fs16\\intbl solide\\cell\\fs16\\intbl Coupe 305\\cell\\fs16\\intbl 5\\cell\\fs16\\intbl 33\\cell\\row\n\\trowd\\clbrdrt\\brdrs\\clbrdrl\\brdrs\\clbrdrb\\brdrs\\clbrdrr\\brdrs\\cellx1000 \\clbrdrt\\brdrs\\clbrdrl\\brdrs\\clbrdrb\\brdrs\\clbrdrr\\brdrs\\cellx2000 \\clbrdrt\\brdrs\\clbrdrl\\brdrs\\clbrdrb\\brdrs\\clbrdrr\\brdrs\\cellx3000\n\\clbrdrt\\brdrs\\clbrdrl\\brdrs\\clbrdrb\\brdrs\\clbrdrr\\brdrs\\cellx4000 \\clbrdrt\\brdrs\\clbrdrl\\brdrs\\clbrdrb\\brdrs\\clbrdrr\\brdrs\\cellx5000\\fs16\\intbl N4\\cell\\fs16\\intbl solide\\cell\\fs16\\intbl Coupe\n303\\cell\\fs16\\intbl 5\\cell\\fs16\\intbl 38\\cell\\row \\trowd\\clbrdrt\\brdrs\\clbrdrl\\brdrs\\clbrdrb\\brdrs\\clbrdrr\\brdrs\\cellx1000 \\clbrdrt\\brdrs\\clbrdrl\\brdrs\\clbrdrb\\brdrs\\clbrdrr\\brdrs\\cellx2000\n\\clbrdrt\\brdrs\\clbrdrl\\brdrs\\clbrdrb\\brdrs\\clbrdrr\\brdrs\\cellx3000 \\clbrdrt\\brdrs\\clbrdrl\\brdrs\\clbrdrb\\brdrs\\clbrdrr\\brdrs\\cellx4000\n\\clbrdrt\\brdrs\\clbrdrl\\brdrs\\clbrdrb\\brdrs\\clbrdrr\\brdrs\\cellx5000\\fs16\\intbl N5\\cell\\fs16\\intbl solide\\cell\\fs16\\intbl Coupe 303\\cell\\fs16\\intbl 11\\cell\\fs16\\intbl 70\\cell\\row\n\\trowd\\clbrdrt\\brdrs\\clbrdrl\\brdrs\\clbrdrb\\brdrs\\clbrdrr\\brdrs\\cellx1000 \\clbrdrt\\brdrs\\clbrdrl\\brdrs\\clbrdrb\\brdrs\\clbrdrr\\brdrs\\cellx2000 \\clbrdrt\\brdrs\\clbrdrl\\brdrs\\clbrdrb\\brdrs\\clbrdrr\\brdrs\\cellx3000\n\\clbrdrt\\brdrs\\clbrdrl\\brdrs\\clbrdrb\\brdrs\\clbrdrr\\brdrs\\cellx4000 \\clbrdrt\\brdrs\\clbrdrl\\brdrs\\clbrdrb\\brdrs\\clbrdrr\\brdrs\\cellx5000\\fs16\\intbl N6\\cell\\fs16\\intbl solide\\cell\\fs16\\intbl Coupe\n297\\cell\\fs16\\intbl 4\\cell\\fs16\\intbl 34\\cell\\row \\trowd\\clbrdrt\\brdrs\\clbrdrl\\brdrs\\clbrdrb\\brdrs\\clbrdrr\\brdrs\\cellx1000 \\clbrdrt\\brdrs\\clbrdrl\\brdrs\\clbrdrb\\brdrs\\clbrdrr\\brdrs\\cellx2000\n\\clbrdrt\\brdrs\\clbrdrl\\brdrs\\clbrdrb\\brdrs\\clbrdrr\\brdrs\\cellx3000 \\clbrdrt\\brdrs\\clbrdrl\\brdrs\\clbrdrb\\brdrs\\clbrdrr\\brdrs\\cellx4000\n\\clbrdrt\\brdrs\\clbrdrl\\brdrs\\clbrdrb\\brdrs\\clbrdrr\\brdrs\\cellx5000\\fs16\\intbl N7\\cell\\fs16\\intbl solide\\cell\\fs16\\intbl Coupe 137\\cell\\fs16\\intbl 6\\cell\\fs16\\intbl 45\\cell\\row\n\\trowd\\clbrdrt\\brdrs\\clbrdrl\\brdrs\\clbrdrb\\brdrs\\clbrdrr\\brdrs\\cellx1000 \\clbrdrt\\brdrs\\clbrdrl\\brdrs\\clbrdrb\\brdrs\\clbrdrr\\brdrs\\cellx2000 \\clbrdrt\\brdrs\\clbrdrl\\brdrs\\clbrdrb\\brdrs\\clbrdrr\\brdrs\\cellx3000\n\\clbrdrt\\brdrs\\clbrdrl\\brdrs\\clbrdrb\\brdrs\\clbrdrr\\brdrs\\cellx4000 \\clbrdrt\\brdrs\\clbrdrl\\brdrs\\clbrdrb\\brdrs\\clbrdrr\\brdrs\\cellx5000\\fs16\\intbl N8\\cell\\fs16\\intbl solide\\cell\\fs16\\intbl Coupe\n94\\cell\\fs16\\intbl 7\\cell\\fs16\\intbl 74\\cell\\row \\trowd\\clbrdrt\\brdrs\\clbrdrl\\brdrs\\clbrdrb\\brdrs\\clbrdrr\\brdrs\\cellx1000 \\clbrdrt\\brdrs\\clbrdrl\\brdrs\\clbrdrb\\brdrs\\clbrdrr\\brdrs\\cellx2000\n\\clbrdrt\\brdrs\\clbrdrl\\brdrs\\clbrdrb\\brdrs\\clbrdrr\\brdrs\\cellx3000 \\clbrdrt\\brdrs\\clbrdrl\\brdrs\\clbrdrb\\brdrs\\clbrdrr\\brdrs\\cellx4000\n\\clbrdrt\\brdrs\\clbrdrl\\brdrs\\clbrdrb\\brdrs\\clbrdrr\\brdrs\\cellx5000\\fs16\\intbl N9\\cell\\fs16\\intbl inconnu\\cell\\fs16\\intbl Coupe 75\\cell\\fs16\\intbl \\cell\\fs16\\intbl \\cell\\row}"
    }
  ]
}

